autowire/__init__.py
autowire/base_container.py
autowire/base_resource.py
autowire/container.py
autowire/context.py
autowire/exc.py
autowire/implementation.py
autowire/provider.py
autowire/py.typed
autowire/resource.py
Autowire-1.1.4.dist-info/METADATA
Autowire-1.1.4.dist-info/WHEEL
Autowire-1.1.4.dist-info/top_level.txt
Autowire-1.1.4.dist-info/RECORD
