Metadata-Version: 2.1
Name: Autowire
Version: 1.1.4
Summary: Simple dependency injection.
Home-page: https://github.com/hardtack/autowire
Author: Choi Geonu
Author-email: 6566gun@gmail.com
License: MIT LICENSE
Keywords: dependency-injection
Platform: UNKNOWN
